<?xml version="1.0" encoding="UTF-8"?>
<!DOCTYPE plist PUBLIC "-//Apple//DTD PLIST 1.0//EN" "http://www.apple.com/DTDs/PropertyList-1.0.dtd"/>

<plist version="1.0">
    <dict>
        <key>ROOT</key>
        <array>
            <dict>
                <key>id</key>
                <string>151</string>
            </dict>
            <dict>
                <key>id</key>
                <string>342</string>
            </dict>
            <dict>
                <key>id</key>
                <string>442</string>
            </dict>
            <dict>
                <key>id</key>
                <string>992</string>
            </dict>
            <dict>
                <key>id</key>
                <string>1043</string>
            </dict>
            <dict>
                <key>id</key>
                <string>1051</string>
            </dict>
            <dict>
                <key>id</key>
                <string>1187</string>
            </dict>
            <dict>
                <key>id</key>
                <string>1611</string>
            </dict>
            <dict>
                <key>id</key>
                <string>1622</string>
            </dict>
            <dict>
                <key>id</key>
                <string>1630</string>
            </dict>
            <dict>
                <key>id</key>
                <string>1812</string>
            </dict>
            <dict>
                <key>id</key>
                <string>1819</string>
            </dict>
            <dict>
                <key>id</key>
                <string>1908</string>
            </dict>
            <dict>
                <key>id</key>
                <string>1989</string>
            </dict>
            <dict>
                <key>id</key>
                <string>1995</string>
            </dict>
            <dict>
                <key>id</key>
                <string>1998</string>
            </dict>
            <dict>
                <key>id</key>
                <string>2003</string>
            </dict>
            <dict>
                <key>id</key>
                <string>2011</string>
            </dict>
            <dict>
                <key>id</key>
                <string>2013</string>
            </dict>
            <dict>
                <key>id</key>
                <string>2020</string>
            </dict>
            <dict>
                <key>id</key>
                <string>2026</string>
            </dict>
            <dict>
                <key>id</key>
                <string>2032</string>
            </dict>
            <dict>
                <key>id</key>
                <string>2035</string>
            </dict>
            <dict>
                <key>id</key>
                <string>2038</string>
            </dict>
            <dict>
                <key>id</key>
                <string>2041</string>
            </dict>
            <dict>
                <key>id</key>
                <string>2048</string>
            </dict>
            <dict>
                <key>id</key>
                <string>2051</string>
            </dict>
            <dict>
                <key>id</key>
                <string>2081</string>
            </dict>
            <dict>
                <key>id</key>
                <string>2084</string>
            </dict>
            <dict>
                <key>id</key>
                <string>2106</string>
            </dict>
            <dict>
                <key>id</key>
                <string>2118</string>
            </dict>
            <dict>
                <key>id</key>
                <string>2158</string>
            </dict>
            <dict>
                <key>id</key>
                <string>2159</string>
            </dict>
            <dict>
                <key>id</key>
                <string>2160</string>
            </dict>
            <dict>
                <key>id</key>
                <string>2161</string>
            </dict>
            <dict>
                <key>id</key>
                <string>2162</string>
            </dict>
            <dict>
                <key>id</key>
                <string>2163</string>
            </dict>
            <dict>
                <key>id</key>
                <string>2164</string>
            </dict>
            <dict>
                <key>id</key>
                <string>2165</string>
            </dict>
            <dict>
                <key>id</key>
                <string>2166</string>
            </dict>
            <dict>
                <key>id</key>
                <string>2167</string>
            </dict>
            <dict>
                <key>id</key>
                <string>2192</string>
            </dict>
            <dict>
                <key>id</key>
                <string>2196</string>
            </dict>
            <dict>
                <key>id</key>
                <string>2223</string>
            </dict>
            <dict>
                <key>id</key>
                <string>2224</string>
            </dict>
            <dict>
                <key>id</key>
                <string>2225</string>
            </dict>
            <dict>
                <key>id</key>
                <string>2226</string>
            </dict>
            <dict>
                <key>id</key>
                <string>2227</string>
            </dict>
            <dict>
                <key>id</key>
                <string>2228</string>
            </dict>
            <dict>
                <key>id</key>
                <string>2229</string>
            </dict>
            <dict>
                <key>id</key>
                <string>2230</string>
            </dict>
            <dict>
                <key>id</key>
                <string>2231</string>
            </dict>
            <dict>
                <key>id</key>
                <string>2232</string>
            </dict>
            <dict>
                <key>id</key>
                <string>2244</string>
            </dict>
            <dict>
                <key>id</key>
                <string>2245</string>
            </dict>
            <dict>
                <key>id</key>
                <string>2246</string>
            </dict>
            <dict>
                <key>id</key>
                <string>2256</string>
            </dict>
            <dict>
                <key>id</key>
                <string>2257</string>
            </dict>
            <dict>
                <key>id</key>
                <string>2258</string>
            </dict>
            <dict>
                <key>id</key>
                <string>2259</string>
            </dict>
            <dict>
                <key>id</key>
                <string>2260</string>
            </dict>
            <dict>
                <key>id</key>
                <string>2261</string>
            </dict>
            <dict>
                <key>id</key>
                <string>2262</string>
            </dict>
            <dict>
                <key>id</key>
                <string>2264</string>
            </dict>
            <dict>
                <key>id</key>
                <string>2279</string>
            </dict>
            <dict>
                <key>id</key>
                <string>2280</string>
            </dict>
            <dict>
                <key>id</key>
                <string>2281</string>
            </dict>
            <dict>
                <key>id</key>
                <string>2282</string>
            </dict>
            <dict>
                <key>id</key>
                <string>2283</string>
            </dict>
            <dict>
                <key>id</key>
                <string>2284</string>
            </dict>
            <dict>
                <key>id</key>
                <string>2285</string>
            </dict>
            <dict>
                <key>id</key>
                <string>2286</string>
            </dict>
            <dict>
                <key>id</key>
                <string>2287</string>
            </dict>
            <dict>
                <key>id</key>
                <string>2288</string>
            </dict>
            <dict>
                <key>id</key>
                <string>2305</string>
            </dict>
            <dict>
                <key>id</key>
                <string>2306</string>
            </dict>
            <dict>
                <key>id</key>
                <string>2307</string>
            </dict>
            <dict>
                <key>id</key>
                <string>2308</string>
            </dict>
            <dict>
                <key>id</key>
                <string>2309</string>
            </dict>
            <dict>
                <key>id</key>
                <string>2310</string>
            </dict>
            <dict>
                <key>id</key>
                <string>2311</string>
            </dict>
            <dict>
                <key>id</key>
                <string>2312</string>
            </dict>
            <dict>
                <key>id</key>
                <string>2313</string>
            </dict>
            <dict>
                <key>id</key>
                <string>2314</string>
            </dict>
            <dict>
                <key>id</key>
                <string>2331</string>
            </dict>
            <dict>
                <key>id</key>
                <string>2454</string>
            </dict>
            <dict>
                <key>id</key>
                <string>2559</string>
            </dict>
            <dict>
                <key>id</key>
                <string>2705</string>
            </dict>
            <dict>
                <key>id</key>
                <string>2743</string>
            </dict>
            <dict>
                <key>id</key>
                <string>2755</string>
            </dict>
            <dict>
                <key>id</key>
                <string>2770</string>
            </dict>
            <dict>
                <key>id</key>
                <string>2820</string>
            </dict>
            <dict>
                <key>id</key>
                <string>2945</string>
            </dict>
            <dict>
                <key>id</key>
                <string>2984</string>
            </dict>
            <dict>
                <key>id</key>
                <string>3087</string>
            </dict>
            <dict>
                <key>id</key>
                <string>3135</string>
            </dict>
            <dict>
                <key>id</key>
                <string>3136</string>
            </dict>
            <dict>
                <key>id</key>
                <string>3137</string>
            </dict>
            <dict>
                <key>id</key>
                <string>3138</string>
            </dict>
            <dict>
                <key>id</key>
                <string>3139</string>
            </dict>
            <dict>
                <key>id</key>
                <string>3140</string>
            </dict>
            <dict>
                <key>id</key>
                <string>3141</string>
            </dict>
            <dict>
                <key>id</key>
                <string>3142</string>
            </dict>
            <dict>
                <key>id</key>
                <string>3143</string>
            </dict>
            <dict>
                <key>id</key>
                <string>3144</string>
            </dict>
            <dict>
                <key>id</key>
                <string>3145</string>
            </dict>
            <dict>
                <key>id</key>
                <string>3146</string>
            </dict>
            <dict>
                <key>id</key>
                <string>3147</string>
            </dict>
            <dict>
                <key>id</key>
                <string>3148</string>
            </dict>
            <dict>
                <key>id</key>
                <string>3149</string>
            </dict>
            <dict>
                <key>id</key>
                <string>3150</string>
            </dict>
            <dict>
                <key>id</key>
                <string>3151</string>
            </dict>
            <dict>
                <key>id</key>
                <string>3174</string>
            </dict>
            <dict>
                <key>id</key>
                <string>3568</string>
            </dict>
            <dict>
                <key>id</key>
                <string>3881</string>
            </dict>
            <dict>
                <key>id</key>
                <string>4407</string>
            </dict>
            <dict>
                <key>id</key>
                <string>4414</string>
            </dict>
            <dict>
                <key>id</key>
                <string>4466</string>
            </dict>
            <dict>
                <key>id</key>
                <string>4467</string>
            </dict>
            <dict>
                <key>id</key>
                <string>4468</string>
            </dict>
            <dict>
                <key>id</key>
                <string>4469</string>
            </dict>
            <dict>
                <key>id</key>
                <string>4470</string>
            </dict>
            <dict>
                <key>id</key>
                <string>4471</string>
            </dict>
            <dict>
                <key>id</key>
                <string>4496</string>
            </dict>
            <dict>
                <key>id</key>
                <string>4529</string>
            </dict>
            <dict>
                <key>id</key>
                <string>5018</string>
            </dict>
            <dict>
                <key>id</key>
                <string>5043</string>
            </dict>
            <dict>
                <key>id</key>
                <string>5054</string>
            </dict>
            <dict>
                <key>id</key>
                <string>5123</string>
            </dict>
            <dict>
                <key>id</key>
                <string>5218</string>
            </dict>
            <dict>
                <key>id</key>
                <string>5219</string>
            </dict>
            <dict>
                <key>id</key>
                <string>5220</string>
            </dict>
            <dict>
                <key>id</key>
                <string>5221</string>
            </dict>
            <dict>
                <key>id</key>
                <string>5222</string>
            </dict>
            <dict>
                <key>id</key>
                <string>5223</string>
            </dict>
            <dict>
                <key>id</key>
                <string>5224</string>
            </dict>
            <dict>
                <key>id</key>
                <string>5225</string>
            </dict>
            <dict>
                <key>id</key>
                <string>5226</string>
            </dict>
            <dict>
                <key>id</key>
                <string>5227</string>
            </dict>
            <dict>
                <key>id</key>
                <string>5228</string>
            </dict>
            <dict>
                <key>id</key>
                <string>5229</string>
            </dict>
            <dict>
                <key>id</key>
                <string>5230</string>
            </dict>
            <dict>
                <key>id</key>
                <string>5231</string>
            </dict>
            <dict>
                <key>id</key>
                <string>5232</string>
            </dict>
            <dict>
                <key>id</key>
                <string>5233</string>
            </dict>
            <dict>
                <key>id</key>
                <string>5234</string>
            </dict>
            <dict>
                <key>id</key>
                <string>5235</string>
            </dict>
            <dict>
                <key>id</key>
                <string>5236</string>
            </dict>
            <dict>
                <key>id</key>
                <string>5237</string>
            </dict>
            <dict>
                <key>id</key>
                <string>5238</string>
            </dict>
            <dict>
                <key>id</key>
                <string>5239</string>
            </dict>
            <dict>
                <key>id</key>
                <string>5240</string>
            </dict>
            <dict>
                <key>id</key>
                <string>5241</string>
            </dict>
            <dict>
                <key>id</key>
                <string>5242</string>
            </dict>
            <dict>
                <key>id</key>
                <string>5243</string>
            </dict>
            <dict>
                <key>id</key>
                <string>5244</string>
            </dict>
            <dict>
                <key>id</key>
                <string>5246</string>
            </dict>
            <dict>
                <key>id</key>
                <string>5247</string>
            </dict>
            <dict>
                <key>id</key>
                <string>5248</string>
            </dict>
            <dict>
                <key>id</key>
                <string>5391</string>
            </dict>
            <dict>
                <key>id</key>
                <string>5402</string>
            </dict>
            <dict>
                <key>id</key>
                <string>5413</string>
            </dict>
            <dict>
                <key>id</key>
                <string>5424</string>
            </dict>
            <dict>
                <key>id</key>
                <string>5435</string>
            </dict>
            <dict>
                <key>id</key>
                <string>5446</string>
            </dict>
            <dict>
                <key>id</key>
                <string>5457</string>
            </dict>
            <dict>
                <key>id</key>
                <string>5899</string>
            </dict>
            <dict>
                <key>id</key>
                <string>5921</string>
            </dict>
            <dict>
                <key>id</key>
                <string>5932</string>
            </dict>
            <dict>
                <key>id</key>
                <string>6067</string>
            </dict>
            <dict>
                <key>id</key>
                <string>6073</string>
            </dict>
            <dict>
                <key>id</key>
                <string>6079</string>
            </dict>
            <dict>
                <key>id</key>
                <string>6085</string>
            </dict>
            <dict>
                <key>id</key>
                <string>6091</string>
            </dict>
            <dict>
                <key>id</key>
                <string>6097</string>
            </dict>
            <dict>
                <key>id</key>
                <string>6103</string>
            </dict>
            <dict>
                <key>id</key>
                <string>6109</string>
            </dict>
            <dict>
                <key>id</key>
                <string>6179</string>
            </dict>
            <dict>
                <key>id</key>
                <string>6185</string>
            </dict>
            <dict>
                <key>id</key>
                <string>6191</string>
            </dict>
            <dict>
                <key>id</key>
                <string>6197</string>
            </dict>
            <dict>
                <key>id</key>
                <string>6203</string>
            </dict>
            <dict>
                <key>id</key>
                <string>6209</string>
            </dict>
            <dict>
                <key>id</key>
                <string>6558</string>
            </dict>
            <dict>
                <key>id</key>
                <string>6564</string>
            </dict>
            <dict>
                <key>id</key>
                <string>6570</string>
            </dict>
            <dict>
                <key>id</key>
                <string>6639</string>
            </dict>
            <dict>
                <key>id</key>
                <string>6762</string>
            </dict>
            <dict>
                <key>id</key>
                <string>6765</string>
            </dict>
            <dict>
                <key>id</key>
                <string>6877</string>
            </dict>
            <dict>
                <key>id</key>
                <string>6888</string>
            </dict>
            <dict>
                <key>id</key>
                <string>6899</string>
            </dict>
            <dict>
                <key>id</key>
                <string>6972</string>
            </dict>
            <dict>
                <key>id</key>
                <string>7184</string>
            </dict>
            <dict>
                <key>id</key>
                <string>7190</string>
            </dict>
            <dict>
                <key>id</key>
                <string>7197</string>
            </dict>
        </array>
    </dict>
</plist>
